mgraph_ai_service_cache_client/__init__.py
mgraph_ai_service_cache_client/client/__init__.py
mgraph_ai_service_cache_client/client/cache_client/Cache__Service__Client.py
mgraph_ai_service_cache_client/client/cache_client/Cache__Service__Client__Requests.py
mgraph_ai_service_cache_client/client/cache_client/__init__.py
mgraph_ai_service_cache_client/client/cache_service/__init__.py
mgraph_ai_service_cache_client/client/cache_service/register_cache_service.py
mgraph_ai_service_cache_client/client/client_contract/__init__.py
mgraph_ai_service_cache_client/client/client_contract/admin/Cache__Service__Client__Admin__Storage.py
mgraph_ai_service_cache_client/client/client_contract/admin/__init__.py
mgraph_ai_service_cache_client/client/client_contract/auth/Cache__Service__Client__Set_Cookie.py
mgraph_ai_service_cache_client/client/client_contract/auth/__init__.py
mgraph_ai_service_cache_client/client/client_contract/data/Cache__Service__Client__Data.py
mgraph_ai_service_cache_client/client/client_contract/data/Cache__Service__Client__Data__Delete.py
mgraph_ai_service_cache_client/client/client_contract/data/Cache__Service__Client__Data__Exists.py
mgraph_ai_service_cache_client/client/client_contract/data/Cache__Service__Client__Data__List.py
mgraph_ai_service_cache_client/client/client_contract/data/Cache__Service__Client__Data__Retrieve.py
mgraph_ai_service_cache_client/client/client_contract/data/Cache__Service__Client__Data__Store.py
mgraph_ai_service_cache_client/client/client_contract/data/Cache__Service__Client__Data__Update.py
mgraph_ai_service_cache_client/client/client_contract/data/__init__.py
mgraph_ai_service_cache_client/client/client_contract/file/Cache__Service__Client__File__Delete.py
mgraph_ai_service_cache_client/client/client_contract/file/Cache__Service__Client__File__Exists.py
mgraph_ai_service_cache_client/client/client_contract/file/Cache__Service__Client__File__Retrieve.py
mgraph_ai_service_cache_client-0.33.0.dist-info/LICENSE
mgraph_ai_service_cache_client-0.33.0.dist-info/METADATA
mgraph_ai_service_cache_client-0.33.0.dist-info/WHEEL
mgraph_ai_service_cache_client-0.33.0.dist-info/RECORD
